polly/__init__.py
polly/analyze.py
polly/application_error_info.py
polly/atlas.py
polly/auth.py
polly/constants.py
polly/curation.py
polly/data_management.py
polly/errors.py
polly/help.py
polly/helpers.py
polly/http_response_codes.py
polly/index_schema_level_conversion_const.py
polly/jobs.py
polly/omixatlas.py
polly/omixatlas_hlpr.py
polly/pipelines.py
polly/polly_kg.py
polly/s3_utils.py
polly/session.py
polly/threading_utils.py
polly/tracking.py
polly/validation.py
polly/validation_hlpr.py
polly/workspaces.py
polly_interfaces/IFiles.py
polly_interfaces/IReporting.py
polly_interfaces/ISchema.py
polly_interfaces/__init__.py
polly_python-4.5.0.dist-info/licenses/LICENSE.md
polly_services/__init__.py
polly_services/dataset.py
polly_services/polly_services_hlpr.py
polly_services/files/__init__.py
polly_services/files/files.py
polly_services/files/files_hlpr.py
polly_services/reporting/__init__.py
polly_services/reporting/reporting.py
polly_services/reporting/reporting_hlpr.py
polly_services/schema/__init__.py
polly_services/schema/schema.py
polly_services/schema/schema_const.py
polly_services/schema/schema_hlpr.py
polly_services/schema/validate_schema_hlpr.py
polly_python-4.5.0.dist-info/METADATA
polly_python-4.5.0.dist-info/WHEEL
polly_python-4.5.0.dist-info/top_level.txt
polly_python-4.5.0.dist-info/RECORD
