Metadata-Version: 2.4
Name: polly_python
Version: 4.5.0
Summary: Polly SDK
Home-page: https://github.com/ElucidataInc/polly-python
Project-URL: Documentation, https://docs.elucidata.io
Project-URL: Tutorial Notebooks, https://github.com/ElucidataInc/polly-python
Requires-Python: <3.15,>=3.9
License-File: LICENSE.md
Requires-Dist: cmapPy==4.0.1
Requires-Dist: cloudpathlib<1.0.0,>=0.19.0
Requires-Dist: retrying==1.3.4
Requires-Dist: rst2txt==1.1.0
Requires-Dist: mixpanel<5.0.0,>=4.10.0
Requires-Dist: Deprecated<2.0.0,>=1.2.12
Requires-Dist: pydantic<3.0.0,>=2.8.2
Requires-Dist: requests<=2.32.3,>=2.31.0
Requires-Dist: boto3<2.0.0,>=1.34.0
Requires-Dist: joblib==1.4.2
Requires-Dist: rich<14.0.0,>=13.0.0
Requires-Dist: tqdm==4.66.4
Requires-Dist: plotly==6.3.1
Requires-Dist: cryptography<=38.0.0; python_full_version >= "3.9.0" and python_full_version <= "3.9.1"
Requires-Dist: cryptography==46.0.2; python_full_version >= "3.9.2"
Requires-Dist: setuptools>=65.0.0; python_version >= "3.12"
Requires-Dist: pandas<=2.2.3,>=1.5.3; python_version == "3.9"
Requires-Dist: pandas<=2.2.3,>=1.5.3; python_version == "3.10"
Requires-Dist: pandas<=2.2.3,>=1.5.3; python_version == "3.11"
Requires-Dist: pandas<=2.2.3,>=2.1.0; python_version == "3.12"
Requires-Dist: pandas<=2.2.3,>=2.2.2; python_version == "3.13"
Requires-Dist: pandas<=2.2.3,>=2.2.2; python_version == "3.14"
Requires-Dist: numpy<=1.25.2,>=1.23.0; python_version == "3.9"
Requires-Dist: numpy<=2.2.2,>=1.23.0; python_version == "3.10"
Requires-Dist: numpy<=2.2.2,>=1.24.0; python_version == "3.11"
Requires-Dist: numpy<=2.2.2,>=1.26.0; python_version == "3.12"
Requires-Dist: numpy<=2.2.2,>=2.2.0; python_version == "3.13"
Requires-Dist: numpy<=2.2.2,>=2.2.0; python_version == "3.14"
Provides-Extra: testing
Requires-Dist: black; extra == "testing"
Requires-Dist: flake8; extra == "testing"
Requires-Dist: pytest; extra == "testing"
Requires-Dist: pytest-mock; extra == "testing"
Requires-Dist: moto; extra == "testing"
Dynamic: license-file
